hladownload/__init__.py
hladownload/__main__.py
hladownload/eplet.py
hladownload/frequency.py
hladownload/hla.py
hladownload-1.1.dist-info/LICENSE
hladownload-1.1.dist-info/METADATA
hladownload-1.1.dist-info/WHEEL
hladownload-1.1.dist-info/entry_points.txt
hladownload-1.1.dist-info/top_level.txt
hladownload-1.1.dist-info/RECORD
