Metadata-Version: 2.1
Name: hladownload
Version: 1.1
Summary: Python command line program and module for retrieving HLA alleles, frequencies and eplets.
Home-page: https://github.com/ramonamerong/hladownload
Author: Ramon van Amerongen
Author-email: ramonamerong@live.nl
Project-URL: Bug Tracker, https://github.com/ramonamerong/hladownload/issues
Classifier: Programming Language :: Python :: 3
Classifier: License :: OSI Approved :: MIT License
Classifier: Operating System :: OS Independent
Requires-Python: >=3.8.5
License-File: LICENSE
Requires-Dist: requests (>=2.25.1)
Requires-Dist: pandas (>=1.2.4)
Requires-Dist: biopython (>=1.78)
Requires-Dist: lxml (>=4.6.3)
